deep_researcher/__init__.py
deep_researcher/deep_research.py
deep_researcher/iterative_research.py
deep_researcher/llm_config.py
deep_researcher/main.py
deep_researcher/agents/__init__.py
deep_researcher/agents/baseclass.py
deep_researcher/agents/knowledge_gap_agent.py
deep_researcher/agents/long_writer_agent.py
deep_researcher/agents/planner_agent.py
deep_researcher/agents/proofreader_agent.py
deep_researcher/agents/thinking_agent.py
deep_researcher/agents/tool_selector_agent.py
deep_researcher/agents/writer_agent.py
deep_researcher/agents/tool_agents/__init__.py
deep_researcher/agents/tool_agents/crawl_agent.py
deep_researcher/agents/tool_agents/search_agent.py
deep_researcher/agents/utils/__init__.py
deep_researcher/agents/utils/parse_output.py
deep_researcher/tools/__init__.py
deep_researcher/tools/crawl_website.py
deep_researcher/tools/web_search.py
deep_researcher/utils/__init__.py
deep_researcher/utils/md_to_pdf.py
deep_researcher/utils/os.py
deep_researcher-0.0.11.dist-info/licenses/LICENSE
tests/__init__.py
tests/config.py
tests/test_model_providers.py
tests/test_reformat_references.py
tests/test_reformat_section_headings.py
tests/test_research_agents.py
tests/test_tool_agents.py
deep_researcher-0.0.11.dist-info/METADATA
deep_researcher-0.0.11.dist-info/WHEEL
deep_researcher-0.0.11.dist-info/entry_points.txt
deep_researcher-0.0.11.dist-info/top_level.txt
deep_researcher-0.0.11.dist-info/RECORD
