Metadata-Version: 2.4
Name: deep-researcher
Version: 0.0.11
Summary: A package for performing deep research using AI agents, implemented using the OpenAI Agents SDK
Home-page: https://github.com/qx-labs/agents-deep-research
Author: Jai Juneja
Author-email: jai@qxlabs.com
Classifier: License :: OSI Approved :: Apache Software License
Classifier: Operating System :: OS Independent
Classifier: Intended Audience :: Developers
Classifier: Intended Audience :: Education
Classifier: Intended Audience :: Science/Research
Classifier: Programming Language :: Python :: 3
Classifier: Topic :: Scientific/Engineering :: Artificial Intelligence
Requires-Python: >=3.10
License-File: LICENSE
Requires-Dist: openai
Requires-Dist: python-dotenv
Requires-Dist: aiohttp
Requires-Dist: asyncio
Requires-Dist: beautifulsoup4
Requires-Dist: lxml
Requires-Dist: pydantic
Requires-Dist: openai-agents
Requires-Dist: md2pdf
Provides-Extra: dev
Requires-Dist: pytest; extra == "dev"
Requires-Dist: pytest-asyncio; extra == "dev"
Dynamic: author
Dynamic: author-email
Dynamic: classifier
Dynamic: description
Dynamic: description-content-type
Dynamic: home-page
Dynamic: license-file
Dynamic: provides-extra
Dynamic: requires-dist
Dynamic: requires-python
Dynamic: summary
